imagedit/__init__.py
imagedit/processing/__init__.py
imagedit/processing/coloration.py
imagedit/processing/effects.py
imagedit/processing/transformation.py
imagedit/utils/__init__.py
imagedit/utils/io.py
imagedit/utils/tools.py
imagedit-0.0.1.dist-info/METADATA
imagedit-0.0.1.dist-info/WHEEL
imagedit-0.0.1.dist-info/top_level.txt
imagedit-0.0.1.dist-info/RECORD
