Metadata-Version: 2.1
Name: imagedit
Version: 0.0.1
Summary: This project belongs to Alexandre Silva. This package is a demo for uploading simulation on the Test Pypi website. Email: alexandresilva18a@gmail.com
Home-page: https://github.com/Alexandre-S-bits/imagedit
Author: Alexandre Silva
Author-email: henrique.map@outlook.com
Requires-Python: >=3.8
